rubysubs/__init__.py
rubysubs/__main__.py
rubysubs/ja_util.py
rubysubs/migaku_parse_ja.py
rubysubs/ruby_parse.py
rubysubs/ruby_subs.py
rubysubs/rubysubs.py
rubysubs/tag_parse_migaku_eu.py
rubysubs/tag_parse_migaku_ja.py
rubysubs/tag_parse_migaku_ja_brs.py
rubysubs/tag_parse_migaku_ja_ext.py
rubysubs/tag_parse_migaku_ko.py
rubysubs/tag_parse_migaku_zh.py
rubysubs/tag_parse_ruby.py
rubysubs/tags.py
rubysubs-0.1.4.dist-info/LICENSE
rubysubs-0.1.4.dist-info/METADATA
rubysubs-0.1.4.dist-info/WHEEL
rubysubs-0.1.4.dist-info/entry_points.txt
rubysubs-0.1.4.dist-info/top_level.txt
rubysubs-0.1.4.dist-info/RECORD
