Metadata-Version: 2.1
Name: rubysubs
Version: 0.1.4
Summary: Tool/library to add ruby text to subtitles
Home-page: https://github.com/RicBent/rubysubs
Author: Bent
Author-email: bent@mail.de
License: UNKNOWN
Platform: UNKNOWN
Classifier: Programming Language :: Python :: 3
Classifier: License :: OSI Approved :: GNU Lesser General Public License v3 (LGPLv3)
Classifier: Operating System :: OS Independent
License-File: LICENSE
Requires-Dist: cchardet
Requires-Dist: pysubs2
Requires-Dist: PyQt5
